ucampostgresvro/DBA.py
ucampostgresvro/__init__.py
ucampostgresvro/__main__.py
ucampostgresvro/ca.crt
ucampostgresvro/exceptions.py
ucampostgresvro/tests/__init__.py
ucampostgresvro/tests/conftest.py
ucampostgresvro/tests/dbconnect.py
ucampostgresvro/tests/test_DB.py
ucampostgresvro/tests/utils.py
ucampostgresvro/tools.py
ucampostgresvro/utils.py
ucampostgresvro-0.2.2.dist-info/LICENSE
ucampostgresvro-0.2.2.dist-info/METADATA
ucampostgresvro-0.2.2.dist-info/WHEEL
ucampostgresvro-0.2.2.dist-info/RECORD
