Metadata-Version: 2.3
Name: ucampostgresvro
Version: 0.2.2
Summary: To connect with postgresql for the billing report
Author: Ishan Mahajan
Author-email: mahanishanmahajan@gmail.com
Requires-Python: >=3.10
Classifier: Programming Language :: Python :: 3
Classifier: Programming Language :: Python :: 3.10
Classifier: Programming Language :: Python :: 3.11
Classifier: Programming Language :: Python :: 3.12
Classifier: Programming Language :: Python :: 3.13
Requires-Dist: psycopg2-binary (>=2.9.10,<3.0.0)
